{ "name" : "Taxonomy" , "children": [ { "name" : "Network Management" , "color" : "#C8C8C8" ,"children": [ { "name" : "Ad-hoc networks" , "size": 3 , "fontColor": "black"},{ "name" : "Wireless & mobile networks" , "size": 19 , "fontColor": "black"},{ "name" : "IP networks" , "size": 243 , "fontColor": "black"},{ "name" : "LANs" , "size": 9 , "fontColor": "black"},{ "name" : "Optical Networks" , "size": 1 , "fontColor": "black"},{ "name" : "Sensor Networks" , "size": 4 , "fontColor": "black"},{ "name" : "Overlay Networks" , "size": 0 , "fontColor": "black"},{ "name" : "Virtual Networks" , "size": 1 , "fontColor": "black"},{ "name" : "Software Defined and Programmable Networks" , "size": 1 , "fontColor": "black"},{ "name" : "Data Center Networks" , "size": 3 , "fontColor": "black"},{ "name" : "Smart Grids" , "size": 1 , "fontColor": "black" } ] },{ "name" : "Service Management" , "color" : "#949494" ,"children": [ { "name" : "Multimedia services (e.g., voice, video)" , "size": 3 , "fontColor": "white"},{ "name" : "Data services (e.g., email, web)" , "size": 19 , "fontColor": "white"},{ "name" : "Hosting (virtual machines)" , "size": 2 , "fontColor": "white"},{ "name" : "Grids" , "size": 0 , "fontColor": "white"},{ "name" : "Cloud services" , "size": 2 , "fontColor": "white"},{ "name" : "Resource provisioning and management" , "size": 2 , "fontColor": "white"},{ "name" : "QoE-centric management" , "size": 3 , "fontColor": "white"},{ "name" : "Service discovery, migration and orchestration" , "size": 2 , "fontColor": "white" } ] },{ "name" : "Business Management" , "color" : "#000000" ,"children": [ { "name" : "Legal & ethical issues" , "size": 2 , "fontColor": "white"},{ "name" : "Process management" , "size": 2 , "fontColor": "white" } ] },{ "name" : "Functional Areas" , "color" : "#ECECEC" ,"children": [ { "name" : "Fault management" , "size": 27 , "fontColor": "black"},{ "name" : "Configuration management" , "size": 18 , "fontColor": "black"},{ "name" : "Accounting management" , "size": 4 , "fontColor": "black"},{ "name" : "Performance management" , "size": 35 , "fontColor": "black"},{ "name" : "Security management" , "size": 203 , "fontColor": "black"},{ "name" : "SLA management" , "size": 2 , "fontColor": "black"},{ "name" : "Event management" , "size": 11 , "fontColor": "black" } ] },{ "name" : "Management Approaches" , "color" : "#777777" ,"children": [ { "name" : "Centralized management" , "size": 2 , "fontColor": "white"},{ "name" : "Distributed management" , "size": 1 , "fontColor": "white"},{ "name" : "Autonomic and self management" , "size": 2 , "fontColor": "white"},{ "name" : "Policy-based management" , "size": 10 , "fontColor": "white"},{ "name" : "Federated network management" , "size": 1 , "fontColor": "white"},{ "name" : "Pro-active management" , "size": 1 , "fontColor": "white"},{ "name" : "Energy-aware network management" , "size": 0 , "fontColor": "white" } ] },{ "name" : "Technologies" , "color" : "#AEAEAE" ,"children": [ { "name" : "Protocols" , "size": 30 , "fontColor": "white"},{ "name" : "Middleware" , "size": 0 , "fontColor": "white"},{ "name" : "Mobile agents" , "size": 0 , "fontColor": "white"},{ "name" : "P2P" , "size": 2 , "fontColor": "white"},{ "name" : "Data, information, and semantic modeling" , "size": 22 , "fontColor": "white"},{ "name" : "Cloud computing" , "size": 3 , "fontColor": "white"},{ "name" : "Internet of Things" , "size": 0 , "fontColor": "white"},{ "name" : "Human Machine interaction" , "size": 48 , "fontColor": "white"},{ "name" : "Operations and Business Support Systems (OSS/BSS)" , "size": 0 , "fontColor": "white"},{ "name" : "Grid" , "size": 1 , "fontColor": "white" } ] },{ "name" : "Methods" , "color" : "#FFFFFF" ,"children": [ { "name" : "Control theories" , "size": 1 , "fontColor": "black"},{ "name" : "Optimization theories" , "size": 2 , "fontColor": "black"},{ "name" : "Economic theories" , "size": 0 , "fontColor": "black"},{ "name" : "Machine learning and genetic algorithms" , "size": 11 , "fontColor": "black"},{ "name" : "Logics" , "size": 0 , "fontColor": "black"},{ "name" : "Probabilistic, stochastic processes, queuing theory" , "size": 10 , "fontColor": "black"},{ "name" : "Simulation" , "size": 22 , "fontColor": "black"},{ "name" : "Experimental approach" , "size": 264 , "fontColor": "black"},{ "name" : "Design" , "size": 262 , "fontColor": "black"},{ "name" : "Monitoring & Measurements" , "size": 95 , "fontColor": "black"},{ "name" : "Data mining and (big) data analytics" , "size": 22 , "fontColor": "black" } ] } ] } 